Workbook

Sheet Cost Estimate
A1: E-ACAM Cost Estimate
A5: Category of Expense | B5: OSP Construction Units | C5: Part Number | D5: Unit Description | E5: Quanity | F5: Lead Times | G5: Price | H5: Total
A6: OSP Materials | B6: FDH - Fieldsmart 144 Cabinet - Clearfield | D6: 288 Cabinet Loaded w/132 SC/ACP | E6: ='Serving Areas'!D15 -> 4 | H6: =G6*E6 -> 0
A7: OSP Materials | B7: FDH - Fieldsmart 288Cabinet - Clearfield | D7: 288 Cabinet Loaded w/276 SC/ACP | E7: ='Serving Areas'!E15 -> 5 | H7: =G7*E7 -> 0
A8: OSP Materials | B8: 1 X 32 Splitter | D8: To be placed by local Operations | E8: ='Serving Areas'!Y15 -> 60 | H8: =G8*E8 -> 0
A9: OSP Materials | B9: Modular Splitter Cassette - Clearfield | D9: 4x1x2 Splitter SC/ACP | E9: =SUM(E6:E7) -> 9 | H9: =G9*E9 -> 0
A10: OSP Materials | B10: BFO24 (Material Cost) | C10: 120243D01 | D10: Buried Fiber Optic Cable, Non Gel filled, Armored | E10: 25000 | H10: =G10*E10 -> 0
A11: OSP Materials | B11: BFO48 (Material Cost) | C11: 120243D01 | D11: Buried Fiber Optic Cable, Non Gel filled, Armored | E11: =SUM('Serving Areas'!G15:H15) -> 252674.83 | H11: =G11*E11 -> 0
A12: OSP Materials | B12: BFO96 (Material Cost) | D12: Buried Fiber Optic Cable, Non Gel filled, Armored | E12: =SUM('Serving Areas'!I15:J15) -> 32087.8 | H12: =G12*E12 -> 0
A13: OSP Materials | B13: BFO144 (Material Cost) | D13: Buried Fiber Optic Cable, Non Gel filled, Armored | E13: =SUM('Serving Areas'!K15:L15) -> 40412.7 | H13: =G13*E13 -> 0
A14: OSP Materials | B14: Innerduct Material Cost | D14: 1.25" SDR | E14: =SUM(E11:E13)*0.25 -> 81293.831 | H14: =G14*E14 -> 0
A15: Contract Labor - Cable Construction Labor | B15: BFO24/48/96/144 (Construction Cost) | D15: Buried Mainline Fiber/Pre-Designated (Bore) Minor materials for this unit include couplers. | E15: =E14 -> 81293.831 | H15: =G15*E15 -> 0
A16: OSP Materials | B16: Hand Hole (Material Costs) | D16: 24X36X24 20K T-rated | E16: ='Serving Areas'!N15 -> 17 | H16: =G16*E16 -> 0
A17: OSP Materials | B17: BDO4 (Material Cost) | D17: Buried Plant Fiber Optic Housing, Stake-Mounted | E17: ='Serving Areas'!O15 -> 773.94412 | H17: =G17*E17 -> 0
A18: OSP Materials | B18: BDO5 (Material Cost) | D18: Buried Plant Fiber Optic Housing, Stake-Mounted | H18: =G18*E18 -> 0
G19: Total OSP | H19: =SUM(H6:H18) -> 0
B21: ISP Installation Units | D21: Equipment Description
A22: ISP Materials | B22: ADTRAN OLT CARD | D22: OLT CARDS,SFP | E22: ='Serving Areas'!V15 -> 7 | H22: =G22*E22 -> 0
G23: Total ISP | H23: =SUM(H22:H22) -> 0
B25: Customer Premise Construction Units | D25: Unit Description
A26: CPE materials | B26: GPON Outdoor ONT/Router | C26: 17600070F1S | D26: ADTRAN TA452 OUTDOOR ONT/SR 400 SERIES. | E26: =E30*0.5 -> 273.6 | H26: =G26*E26 -> 0
A27: CPE materials | B27: GPON Outdoor ONT/Router | D27: ONT SDX 611 2ND GEN GPON SFU | E27: =E30*0.5 -> 273.6
A28: CPE materials | B28: SDG 8612 | C28: 17600071F1S | D28: SDG 8612 SmartOS Dual-band 4+4 WiFi-6, 1x 2.5GbE WAN, 1x 2.5GbE + 3x GbE LAN RG, PSU-NA, CC-US | E28: 250 | H28: =G28*E27 -> 0
A29: CPE materials | B29: SDG 8614 | C29: 17600071F1S | D29: SDG 8614 SmartOS Dual-band 4+4 WiFi-6, 1x SFP+ (2.5Gbps) WAN, 1x 2.5GbE + 3x GbE LAN RG, PSU-NA, CC-US | E29: 250
A30: CPE materials | B30: WiFi Gateway | D30: Zyxel 3927 Dual Band | E30: ='Serving Areas'!B15*0.6 -> 547.2 | H30: =G30*E30 -> 0
A31: CPE materials | B31: WiFi Gateway | D31: Zyxel VMG4510 | E31: 1 | H31: =G31*E31 -> 0
A32: CPE materials | B32: Outdoor Network Interface Housing | D32: Outdoor NID TA350 SFU NID ONT | E32: =E30 -> 547.2 | H32: =G32*E32 -> 0
A33: OSP Materials | B33: 2 Fiber Drop (Material Cost) | E33: ='Serving Areas'!Q15 -> 191520 | H33: =G33*E33 -> 0
A34: Contract Labor - Drop Placement | B34: Fiber Drop (Construction Cost) | D34: Place fiber drop, place NID and protective cane if needed | E34: ='Serving Areas'!Q15 -> 191520 | H34: =G34*E34 -> 0
A35: CPE materials | B35: Surge Protector | E35: =E30 -> 547.2 | H35: =G35*E35 -> 0
G36: Total CPE | H36: =SUM(H26:H35) -> 0
B40: Total Infrastructure E-ACAM Estimate | H40: =H36+H23+H19 -> 0
A42: Total Capital FTTH Project Total | H42: =H40 -> 0
A43: Average Cost/Passing EACAM ONLY | H43: =H40/'Serving Areas'!B15 -> 0
A44: Average Cost/Passing Including Non-EACAM | H44: =H40/SUM('Serving Areas'!B15,'Serving Areas'!Z15) -> 0
A45: Cost per Route Mile | H45: =H19/(SUM(E11:E13)/5280) -> 0

Sheet Serving Areas
A1: Splitter Serving Area | B1: Locations | C1: 48-96 Splitter PED | D1: 144 Splitter Cabinet | E1: 288 Splitter Cabinet | F1: BFO 24 Const | G1: BFO 48 Const | H1: BFO 48 COIL | I1: BFO 96 Const | J1: BFO 96 COIL | K1: BFO 144 Const | L1: BFO 144 COIL | M1: Buried Laterals | N1: Hand Holes | O1: BDO4S Pedestals | P1: Fiber Closures | Q1: Drop Footage | R1: Railroad Permits | S1: National Forest Permits | T1: 60% TAKE | U1: DROPS | V1: OLT | W1: SCM-UPGRADE | X1: SM40-UPGRADE | Y1: 1X32 | Z1: NON-EACAM PASSING
A2: 23D1 | B2: 37 | E2: 1 | G2: 15657 | H2: =(G2/400) *15 -> 587.1375 | J2: =(I2/400) *15 -> 0 | K2: 10369 | L2: =(K2/400) *15 -> 388.8375 | N2: 5 | O2: =SUM(G2:K2)/400 -> 66.532844 | P2: 1 | Q2: =350*(B2*0.6) -> 7770 | T2: =B2*0.6 -> 22.2 | U2: 22 | V2: 1 | Y2: 8 | Z2: 34
A3: BD1 | B3: 198 | E3: 1 | G3: 42883 | H3: =(G3/400) *15 -> 1608.1125 | I3: 19272 | J3: =(I3/400) *15 -> 722.7 | K3: 8258 | L3: =(K3/400) *15 -> 309.675 | N3: 1 | O3: =SUM(G3:K3)/400 -> 181.85953 | P3: 1 | Q3: =350*(B3*0.6) -> 41580 | T3: =B3*0.6 -> 118.8 | U3: 464 | V3: 2 | Y3: 8 | Z3: 9
A4: BD2 | B4: 118 | D4: 1 | G4: 30449 | H4: =(G4/400) *15 -> 1141.8375 | J4: =(I4/400) *15 -> 0 | K4: 8120 | L4: =(K4/400) *15 -> 304.5 | N4: 3 | O4: =SUM(G4:K4)/400 -> 99.277094 | Q4: =350*(B4*0.6) -> 24780 | T4: =B4*0.6 -> 70.8 | Y4: 5 | Z4: 8
A5: BD3 | B5: 11 | E5: 1 | G5: 4172 | H5: =(G5/400) *15 -> 156.45 | J5: =(I5/400) *15 -> 0 | K5: 12205 | L5: =(K5/400) *15 -> 457.6875 | N5: 1 | O5: =SUM(G5:K5)/400 -> 41.333625 | Q5: =350*(B5*0.6) -> 2310 | T5: =B5*0.6 -> 6.6 | U5: 8 | Y5: 8
A6: CLETE1 | B6: 45 | D6: 1 | G6: 22800 | H6: =(G6/400) *15 -> 855 | J6: =(I6/400) *15 -> 0 | L6: =(K6/400) *15 -> 0 | N6: 1 | O6: =SUM(G6:K6)/400 -> 59.1375 | P6: 1 | Q6: =350*(B6*0.6) -> 9450 | T6: =B6*0.6 -> 27 | V6: 1 | Y6: 5 | Z6: 2
A7: CLETE2 | B7: 37 | D7: 1 | G7: 23046 | H7: =(G7/400) *15 -> 864.225 | J7: =(I7/400) *15 -> 0 | L7: =(K7/400) *15 -> 0 | N7: 3 | O7: =SUM(G7:K7)/400 -> 59.775562 | Q7: =350*(B7*0.6) -> 7770 | T7: =B7*0.6 -> 22.2 | Y7: 5
A8: CREWS_N | B8: 145 | E8: 1 | G8: 30021 | H8: =(G8/400) *15 -> 1125.7875 | I8: 3679 | J8: =(I8/400) *15 -> 137.9625 | L8: =(K8/400) *15 -> 0 | N8: 1 | O8: =SUM(G8:K8)/400 -> 87.409375 | P8: 1 | Q8: =350*(B8*0.6) -> 30450 | T8: =B8*0.6 -> 87 | V8: 1 | Y8: 8 | Z8: 13
A9: CREWS_S | B9: 154 | E9: 1 | G9: 29247 | H9: =(G9/400) *15 -> 1096.7625 | I9: 7977 | J9: =(I9/400) *15 -> 299.1375 | L9: =(K9/400) *15 -> 0 | N9: 1 | O9: =SUM(G9:K9)/400 -> 96.54975 | P9: 1 | Q9: =350*(B9*0.6) -> 32340 | T9: =B9*0.6 -> 92.4 | V9: 1 | Y9: 8 | Z9: 9
A10: MUD1 | B10: 67 | D10: 1 | G10: 17984 | H10: =(G10/400) *15 -> 674.4 | J10: =(I10/400) *15 -> 0 | L10: =(K10/400) *15 -> 0 | N10: 1 | O10: =SUM(G10:K10)/400 -> 46.646 | P10: 1 | Q10: =350*(B10*0.6) -> 14070 | T10: =B10*0.6 -> 40.2 | U10: 40 | V10: 1 | Y10: 5
A11: EXT-BAXTER | B11: 10 | G11: 4942 | H11: =(G11/400) *15 -> 185.325 | J11: =(I11/400) *15 -> 0 | L11: =(K11/400) *15 -> 0 | O11: =SUM(G11:K11)/400 -> 12.818312 | Q11: =350*(B11*0.6) -> 2100 | T11: =B11*0.6 -> 6 | Z11: 3
A12: EXT-N RAULERSON | B12: 10 | G12: 5010 | H12: =(G12/400) *15 -> 187.875 | J12: =(I12/400) *15 -> 0 | L12: =(K12/400) *15 -> 0 | O12: =SUM(G12:K12)/400 -> 12.994687 | Q12: =350*(B12*0.6) -> 2100 | T12: =B12*0.6 -> 6
A13: EXT-ALTMANS WAY | B13: 20 | G13: 3705 | H13: =(G13/400) *15 -> 138.9375 | J13: =(I13/400) *15 -> 0 | L13: =(K13/400) *15 -> 0 | O13: =SUM(G13:K13)/400 -> 9.6098437 | Q13: =350*(B13*0.6) -> 4200 | T13: =B13*0.6 -> 12 | Z13: 2
A14: EXT-CUYLER FIELD | B14: 60 | G14: 13626 | H14: =(G14/400) *15 -> 510.975 | J14: =(I14/400) *15 -> 0 | L14: =(K14/400) *15 -> 0 | Q14: =350*(B14*0.6) -> 12600 | T14: =B14*0.6 -> 36 | Z14: 4
A15: Totals | B15: =SUM(B2:B14) -> 912 | C15: =SUM(C2:C14) -> 0 | D15: =SUM(D2:D14) -> 4 | E15: =SUM(E2:E14) -> 5 | F15: =SUM(F2:F14) -> 0 | G15: =SUM(G2:G14) -> 243542 | H15: =SUM(H2:H14) -> 9132.825 | I15: =SUM(I2:I14) -> 30928 | ... S15: =SUM(S2:S14) -> 0 | U15: =SUM(U2:U14) -> 534 | V15: =SUM(V2:V14) -> 7 | Y15: =SUM(Y2:Y14) -> 60 | Z15: =SUM(Z2:Z14) -> 84
